genotype/__init__.py
genotype/model.py
genotype/py.typed
genotype_runtime-0.4.0.dist-info/METADATA
genotype_runtime-0.4.0.dist-info/WHEEL
genotype_runtime-0.4.0.dist-info/RECORD
