Metadata-Version: 2.1
Name: genotype-runtime
Version: 0.4.0
Summary: Genotype runtime for Python
License: MIT
Author: Sasha Koss
Author-email: koss@nocorp.me
Requires-Python: >=3.8,<4.0
Classifier: License :: OSI Approved :: MIT License
Classifier: Programming Language :: Python :: 3
Classifier: Programming Language :: Python :: 3.8
Classifier: Programming Language :: Python :: 3.9
Classifier: Programming Language :: Python :: 3.10
Classifier: Programming Language :: Python :: 3.11
Classifier: Programming Language :: Python :: 3.12
Classifier: Programming Language :: Python :: 3.13
Requires-Dist: pydantic (>=2,<3)
Requires-Dist: pyhumps (>=3,<4)
